nonebot_plugin_songpicker2/__init__.py
nonebot_plugin_songpicker2/data_source.py
nonebot_plugin_songpicker2-0.2.6.dist-info/LICENSE
nonebot_plugin_songpicker2-0.2.6.dist-info/METADATA
nonebot_plugin_songpicker2-0.2.6.dist-info/WHEEL
nonebot_plugin_songpicker2-0.2.6.dist-info/RECORD
