Metadata-Version: 2.1
Name: nonebot-plugin-songpicker2
Version: 0.2.6
Summary: 点播歌曲，支持候选菜单、热评显示，数据源为网易云
Home-page: https://github.com/maxesisn/nonebot_plugin_songpicker2
Author: Maximilian Wu
Author-email: me@maxng.cc
Requires-Python: >=3.9,<4.0
Classifier: Programming Language :: Python :: 3
Classifier: Programming Language :: Python :: 3.9
Classifier: Programming Language :: Python :: 3.10
Classifier: Programming Language :: Python :: 3.11
Requires-Dist: build (>=0.1.0,<0.2.0)
Requires-Dist: httpx (>=0.21.3,<0.22.0)
Requires-Dist: nonebot-adapter-onebot (>=2.0.0,<3.0.0)
Requires-Dist: nonebot2 (>=2.0.0,<3.0.0)
Requires-Dist: twine (>=3.3.0,<4.0.0)
Project-URL: Repository, https://github.com/maxesisn/nonebot_plugin_songpicker2
